SecureHTTP.py
SecureHTTP-0.5.0.data/scripts/generate_rsa_keys.sh
SecureHTTP-0.5.0.dist-info/LICENSE
SecureHTTP-0.5.0.dist-info/METADATA
SecureHTTP-0.5.0.dist-info/WHEEL
SecureHTTP-0.5.0.dist-info/entry_points.txt
SecureHTTP-0.5.0.dist-info/top_level.txt
SecureHTTP-0.5.0.dist-info/RECORD
