Metadata-Version: 2.1
Name: SecureHTTP
Version: 0.5.0
Summary: Make HTTP transmissions more secure, encrypted communication for C/S architecture.
Home-page: https://github.com/staugur/Python-SecureHTTP
Author: staugur
Author-email: staugur@saintic.com
License: BSD 3-Clause
Download-URL: https://github.com/staugur/Python-SecureHTTP/releases/tag/v0.5.0
Keywords: RSA,AES,MD5,HTTP
Platform: any
Classifier: Development Status :: 5 - Production/Stable
Classifier: Environment :: Web Environment
Classifier: Intended Audience :: Developers
Classifier: License :: OSI Approved :: BSD License
Classifier: Operating System :: OS Independent
Classifier: Programming Language :: Python :: 2.7
Classifier: Programming Language :: Python :: 3.4
Classifier: Programming Language :: Python :: 3.5
Classifier: Programming Language :: Python :: 3.6
Classifier: Programming Language :: Python :: Implementation :: CPython
Classifier: Programming Language :: Python :: Implementation :: PyPy
Classifier: Topic :: Internet :: WWW/HTTP :: Dynamic Content
Classifier: Topic :: Software Development :: Libraries :: Python Modules
Requires-Dist: pycryptodomex (>=3.7.2)
